canine.py
python_can_canine-0.2.5.dist-info/METADATA
python_can_canine-0.2.5.dist-info/WHEEL
python_can_canine-0.2.5.dist-info/entry_points.txt
python_can_canine-0.2.5.dist-info/top_level.txt
python_can_canine-0.2.5.dist-info/RECORD
