Metadata-Version: 2.1
Name: python-can-canine
Version: 0.2.5
Summary: Python-can CANine
Home-page: https://github.com/yconst/python-can-canine
Author: Yannis Chatzikonstantinou
Author-email: info@tinymovr.com
License: UNKNOWN
Platform: UNKNOWN
Requires-Python: >=3.9
Requires-Dist: python-can
Requires-Dist: pyusb (~=1.0)
